Metadata-Version: 2.1
Name: binogauss-distributions
Version: 0.1
Summary: Gaussian and Binomial distributions
Home-page: UNKNOWN
Author: Samson Tontoye
Author-email: godfatherfigure1@gmail.com
License: UNKNOWN
Platform: UNKNOWN
